graph_widget/__init__.py
graph_widget/dev.py
graph_widget/static/widget.css
graph_widget/static/widget.js
graph_widget-0.1.16.dist-info/METADATA
graph_widget-0.1.16.dist-info/WHEEL
graph_widget-0.1.16.dist-info/RECORD
