Metadata-Version: 2.4
Name: graph_widget
Version: 0.1.16
Requires-Dist: anywidget
Requires-Dist: marimo
